[
  {
    "symbol": "BTCUSDT",
    "leverage": "100",
    "breakEvenPrice": "81671.38914402",
    "autoAddMargin": 0,
    "avgPrice": "81581.6",
    "liqPrice": "80059.60370285",
    "riskLimitValue": "2000000",
    "takeProfit": "82855.7",
    "positionValue": "81.5981",
    "isReduceOnly": false,
    "positionIMByMp": "0.86040218",
    "tpslMode": "Full",
    "riskId": 1,
    "trailingStop": "0",
    "liqPriceByMp": "",
    "unrealisedPnl": "0.0165",
    "markPrice": "81598.1",
    "adlRankIndicator": 2,
    "cumRealisedPnl": "-0.12096105",
    "positionMM": "0.45241168",
    "createdTime": "1777639794596",
    "positionIdx": 0,
    "openTime": 1778011607900,
    "positionIM": "0.86040218",
    "positionMMByMp": "0.45241168",
    "seq": 570548370780,
    "updatedTime": "1778011607900",
    "side": "Buy",
    "bustPrice": "",
    "positionBalance": "0",
    "leverageSysUpdatedTime": "",
    "curRealisedPnl": "-0.04486988",
    "size": "0.001",
    "positionStatus": "Normal",
    "mmrSysUpdatedTime": "",
    "stopLoss": "80814.9",
    "tradeMode": 0,
    "sessionAvgPrice": ""
  }
]